applied_stats/__init__.py
applied_stats/confidence_intervals.py
applied_stats/continuous_distributions.py
applied_stats/hypothesis_testing.py
applied_stats/mle.py
applied_stats-1.0.0.dist-info/LICENSE.txt
applied_stats-1.0.0.dist-info/METADATA
applied_stats-1.0.0.dist-info/WHEEL
applied_stats-1.0.0.dist-info/top_level.txt
applied_stats-1.0.0.dist-info/RECORD
