Metadata-Version: 2.1
Name: applied-stats
Version: 1.0.0
Summary: A basic statistics module to compute MLEs / probabilities
Home-page: https://github.com/WillTirone/applied_stats
Author: William Tirone
Author-email: will.tirone1@gmail.com
License: UNKNOWN
Platform: UNKNOWN
Classifier: Development Status :: 3 - Alpha
Classifier: Intended Audience :: Developers
Classifier: Topic :: Scientific/Engineering :: Mathematics
Classifier: License :: OSI Approved :: MIT License
Classifier: Programming Language :: Python :: 3
Classifier: Programming Language :: Python :: 3.6
Classifier: Programming Language :: Python :: 3.7
Classifier: Programming Language :: Python :: 3.8
Classifier: Programming Language :: Python :: 3.9
Classifier: Programming Language :: Python :: 3 :: Only
Classifier: Operating System :: OS Independent
Requires-Dist: scipy (>1)
Requires-Dist: numpy (>1)
Requires-Dist: matplotlib (>3)
